dataset_sh_server/__init__.py
dataset_sh_server/app.py
dataset_sh_server/auth.py
dataset_sh_server/cli.py
dataset_sh_server/config.py
dataset_sh_server/core.py
dataset_sh_server/project_file_manager.py
dataset_sh_server/utils.py
dataset_sh_server/assets/__init__.py
dataset_sh_server/assets/app-ui.frontend
dataset_sh_server-0.0.5.dist-info/METADATA
dataset_sh_server-0.0.5.dist-info/WHEEL
dataset_sh_server-0.0.5.dist-info/entry_points.txt
dataset_sh_server-0.0.5.dist-info/RECORD
