Metadata-Version: 2.1
Name: dataset_sh_server
Version: 0.0.5
Summary: Dataset.sh server
Project-URL: Homepage, https://dataset.sh
Project-URL: Bug Tracker, https://github.com/dataset-sh/dataset-sh
Author-email: Hao Wu <haowu@dataset.sh>
License: MIT License
Classifier: License :: OSI Approved :: MIT License
Classifier: Operating System :: OS Independent
Classifier: Programming Language :: Python :: 3
Classifier: Topic :: Scientific/Engineering :: Artificial Intelligence
Classifier: Topic :: Scientific/Engineering :: Information Analysis
Requires-Python: >=3.9
Requires-Dist: celery~=5.3.6
Requires-Dist: dataset-sh>=0.0.12
Requires-Dist: flask>=2.0.0
Requires-Dist: head-switcher>=0.0.1
Requires-Dist: pydantic~=2.0.0
Requires-Dist: pyjwt~=2.8.0
Requires-Dist: pyyaml~=6.0.1
